<?xml version="1.0" encoding="utf-8"?>
<TREENODES>
  <treenode1 text="前台首頁資料管理" IMAGEURL="images/User.gif" EXPANDEDIMAGEURL="images/folderopen.gif" id="N_626" Qlevel="0" Ilevel="0" Ulevel="0" Dlevel="0" Clevel="0">
    <treenode2 text="最新消息管理" IMAGEURL="images/User.gif" EXPANDEDIMAGEURL="images/folderopen.gif" id="N_634" Qlevel="0" Ilevel="0" Ulevel="0" Dlevel="0" Clevel="0" />
    <treenode2 text="公司訊息管理" IMAGEURL="images/User.gif" EXPANDEDIMAGEURL="images/folderopen.gif" id="N_636" Qlevel="0" Ilevel="0" Ulevel="0" Dlevel="0" Clevel="0" />
    <treenode2 text="施工通告管理" IMAGEURL="images/User.gif" EXPANDEDIMAGEURL="images/folderopen.gif" id="N_637" Qlevel="0" Ilevel="0" Ulevel="0" Dlevel="0" Clevel="0" />
    <treenode2 text="停氣公告管理" IMAGEURL="images/User.gif" EXPANDEDIMAGEURL="images/folderopen.gif" id="N_638" Qlevel="0" Ilevel="0" Ulevel="0" Dlevel="0" Clevel="0" />
    <treenode2 text="跑馬燈管理" IMAGEURL="images/User.gif" EXPANDEDIMAGEURL="images/folderopen.gif" id="N_639" Qlevel="0" Ilevel="0" Ulevel="0" Dlevel="0" Clevel="0" />
  </treenode1>
  <treenode1 text="下載專區管理" IMAGEURL="images/User.gif" EXPANDEDIMAGEURL="images/folderopen.gif" id="N_628" Qlevel="0" Ilevel="0" Ulevel="0" Dlevel="0" Clevel="0">
    <treenode2 text="下載群組管理" IMAGEURL="images/User.gif" EXPANDEDIMAGEURL="images/folderopen.gif" id="N_640" Qlevel="0" Ilevel="0" Ulevel="0" Dlevel="0" Clevel="0" />
    <treenode2 text="下載資料管理" IMAGEURL="images/User.gif" EXPANDEDIMAGEURL="images/folderopen.gif" id="N_641" Qlevel="0" Ilevel="0" Ulevel="0" Dlevel="0" Clevel="0" />
  </treenode1>
  <treenode1 text="產品管理" IMAGEURL="images/User.gif" EXPANDEDIMAGEURL="images/folderopen.gif" id="N_629" Qlevel="0" Ilevel="0" Ulevel="0" Dlevel="0" Clevel="0">
    <treenode2 text="產品群組管理" IMAGEURL="images/User.gif" EXPANDEDIMAGEURL="images/folderopen.gif" id="N_642" Qlevel="0" Ilevel="0" Ulevel="0" Dlevel="0" Clevel="0" />
    <treenode2 text="產品資料管理" IMAGEURL="images/User.gif" EXPANDEDIMAGEURL="images/folderopen.gif" id="N_643" Qlevel="0" Ilevel="0" Ulevel="0" Dlevel="0" Clevel="0" />
  </treenode1>
  <treenode1 text="常見問題(FAQ)管理" IMAGEURL="images/User.gif" EXPANDEDIMAGEURL="images/folderopen.gif" id="N_630" Qlevel="0" Ilevel="0" Ulevel="0" Dlevel="0" Clevel="0">
    <treenode2 text="問題群組管理" IMAGEURL="images/User.gif" EXPANDEDIMAGEURL="images/folderopen.gif" id="N_644" Qlevel="0" Ilevel="0" Ulevel="0" Dlevel="0" Clevel="0" />
    <treenode2 text="問題資料管理" IMAGEURL="images/User.gif" EXPANDEDIMAGEURL="images/folderopen.gif" id="N_645" Qlevel="0" Ilevel="0" Ulevel="0" Dlevel="0" Clevel="0" />
  </treenode1>
  <treenode1 text="投資人訊息管理" IMAGEURL="images/User.gif" EXPANDEDIMAGEURL="images/folderopen.gif" id="N_632" Qlevel="0" Ilevel="0" Ulevel="0" Dlevel="0" Clevel="0">
    <treenode2 text="董事會會議記錄管理" IMAGEURL="images/User.gif" EXPANDEDIMAGEURL="images/folderopen.gif" id="N_648" Qlevel="0" Ilevel="0" Ulevel="0" Dlevel="0" Clevel="0" />
    <treenode2 text="股東會檔案管理" IMAGEURL="images/User.gif" EXPANDEDIMAGEURL="images/folderopen.gif" id="N_688" Qlevel="0" Ilevel="0" Ulevel="0" Dlevel="0" Clevel="0" />
    <treenode2 text="每月營業額資料管理" IMAGEURL="images/User.gif" EXPANDEDIMAGEURL="images/folderopen.gif" id="N_689" Qlevel="0" Ilevel="0" Ulevel="0" Dlevel="0" Clevel="0" />
    <treenode2 text="近五年財務報告書管理" IMAGEURL="images/User.gif" EXPANDEDIMAGEURL="images/folderopen.gif" id="N_690" Qlevel="0" Ilevel="0" Ulevel="0" Dlevel="0" Clevel="0" />
    <treenode2 text="股利發放相關資訊管理" IMAGEURL="images/User.gif" EXPANDEDIMAGEURL="images/folderopen.gif" id="N_691" Qlevel="0" Ilevel="0" Ulevel="0" Dlevel="0" Clevel="0" />
    <treenode2 text="投資人訊息檔案管理" IMAGEURL="images/User.gif" EXPANDEDIMAGEURL="images/folderopen.gif" id="N_692" Qlevel="0" Ilevel="0" Ulevel="0" Dlevel="0" Clevel="0" />
  </treenode1>
  <treenode1 text="用戶服務管理" IMAGEURL="images/User.gif" EXPANDEDIMAGEURL="images/folderopen.gif" id="N_633" Qlevel="0" Ilevel="0" Ulevel="0" Dlevel="0" Clevel="0">
    <treenode2 text="新用戶申請查詢" IMAGEURL="images/User.gif" EXPANDEDIMAGEURL="images/folderopen.gif" id="N_650" Qlevel="0" Ilevel="0" Ulevel="0" Dlevel="0" Clevel="0" />
    <treenode2 text="自報度數查詢" IMAGEURL="images/User.gif" EXPANDEDIMAGEURL="images/folderopen.gif" id="N_651" Qlevel="0" Ilevel="0" Ulevel="0" Dlevel="0" Clevel="0" />
    <treenode2 text="自報度數查詢 (抄表員用)" IMAGEURL="images/User.gif" EXPANDEDIMAGEURL="images/folderopen.gif" id="N_664" Qlevel="0" Ilevel="0" Ulevel="0" Dlevel="0" Clevel="0" />
    <treenode2 text="自報度數管道查詢(RR00)" IMAGEURL="images/User.gif" EXPANDEDIMAGEURL="images/folderopen.gif" id="N_693" Qlevel="0" Ilevel="0" Ulevel="0" Dlevel="0" Clevel="0" />
  </treenode1>
  <treenode1 text="意見反映管理" IMAGEURL="images/User.gif" EXPANDEDIMAGEURL="images/folderopen.gif" id="N_656" Qlevel="0" Ilevel="0" Ulevel="0" Dlevel="0" Clevel="0">
    <treenode2 text="1.處理意見反映" IMAGEURL="images/User.gif" EXPANDEDIMAGEURL="images/folderopen.gif" id="N_631" Qlevel="0" Ilevel="0" Ulevel="0" Dlevel="0" Clevel="0" />
    <treenode2 text="2.指派意見反映" IMAGEURL="images/User.gif" EXPANDEDIMAGEURL="images/folderopen.gif" id="N_655" Qlevel="0" Ilevel="0" Ulevel="0" Dlevel="0" Clevel="0" />
    <treenode2 text="3.列印意見反映表" IMAGEURL="images/User.gif" EXPANDEDIMAGEURL="images/folderopen.gif" id="N_658" Qlevel="0" Ilevel="0" Ulevel="0" Dlevel="0" Clevel="0" />
  </treenode1>
  <treenode1 text="會員資料管理" IMAGEURL="images/User.gif" EXPANDEDIMAGEURL="images/folderopen.gif" id="N_667" Qlevel="0" Ilevel="0" Ulevel="0" Dlevel="0" Clevel="0">
    <treenode2 text="會員註冊狀態查詢" IMAGEURL="images/User.gif" EXPANDEDIMAGEURL="images/folderopen.gif" id="N_668" Qlevel="0" Ilevel="0" Ulevel="0" Dlevel="0" Clevel="0" />
    <treenode2 text="會員基本資料管理" IMAGEURL="images/User.gif" EXPANDEDIMAGEURL="images/folderopen.gif" id="N_669" Qlevel="0" Ilevel="0" Ulevel="0" Dlevel="0" Clevel="0" />
    <treenode2 text="會員用戶號碼管理" IMAGEURL="images/User.gif" EXPANDEDIMAGEURL="images/folderopen.gif" id="N_670" Qlevel="0" Ilevel="0" Ulevel="0" Dlevel="0" Clevel="0" />
    <treenode2 text="會員修改資料記錄查詢" IMAGEURL="images/User.gif" EXPANDEDIMAGEURL="images/folderopen.gif" id="N_671" Qlevel="0" Ilevel="0" Ulevel="0" Dlevel="0" Clevel="0" />
    <treenode2 text="會員資料轉入MIS作業" IMAGEURL="images/User.gif" EXPANDEDIMAGEURL="images/folderopen.gif" id="N_681" Qlevel="0" Ilevel="0" Ulevel="0" Dlevel="0" Clevel="0" />
    <treenode2 text="會員異動資料明細表" IMAGEURL="images/User.gif" EXPANDEDIMAGEURL="images/folderopen.gif" id="N_682" Qlevel="0" Ilevel="0" Ulevel="0" Dlevel="0" Clevel="0" />
    <treenode2 text="查詢批次刪除拆表與終止戶資料" IMAGEURL="images/User.gif" EXPANDEDIMAGEURL="images/folderopen.gif" id="N_683" Qlevel="0" Ilevel="0" Ulevel="0" Dlevel="0" Clevel="0" />
    <treenode2 text="用戶號碼多次新增明細" IMAGEURL="images/User.gif" EXPANDEDIMAGEURL="images/folderopen.gif" id="N_695" Qlevel="0" Ilevel="0" Ulevel="0" Dlevel="0" Clevel="0" />
  </treenode1>
  <treenode1 text="電子繳費憑證管理" IMAGEURL="images/User.gif" EXPANDEDIMAGEURL="images/folderopen.gif" id="N_673" Qlevel="0" Ilevel="0" Ulevel="0" Dlevel="0" Clevel="0">
    <treenode2 text="電子繳費憑證批次發送記錄查詢" IMAGEURL="images/User.gif" EXPANDEDIMAGEURL="images/folderopen.gif" id="N_674" Qlevel="0" Ilevel="0" Ulevel="0" Dlevel="0" Clevel="0" />
    <treenode2 text="電子繳費憑證發送記錄管理" IMAGEURL="images/User.gif" EXPANDEDIMAGEURL="images/folderopen.gif" id="N_675" Qlevel="0" Ilevel="0" Ulevel="0" Dlevel="0" Clevel="0" />
    <treenode2 text="查詢用戶歷史交易資料" IMAGEURL="images/User.gif" EXPANDEDIMAGEURL="images/folderopen.gif" id="N_676" Qlevel="0" Ilevel="0" Ulevel="0" Dlevel="0" Clevel="0" />
    <treenode2 text="批次寄送電子繳費憑證作業" IMAGEURL="images/User.gif" EXPANDEDIMAGEURL="images/folderopen.gif" id="N_677" Qlevel="0" Ilevel="0" Ulevel="0" Dlevel="0" Clevel="0" />
    <treenode2 text="批次作業查詢" IMAGEURL="images/User.gif" EXPANDEDIMAGEURL="images/folderopen.gif" id="N_678" Qlevel="0" Ilevel="0" Ulevel="0" Dlevel="0" Clevel="0" />
    <treenode2 text="繳費憑證廣告文字管理" IMAGEURL="images/User.gif" EXPANDEDIMAGEURL="images/folderopen.gif" id="N_679" Qlevel="0" Ilevel="0" Ulevel="0" Dlevel="0" Clevel="0" />
    <treenode2 text="繳費憑證注意事項電話內容管理" IMAGEURL="images/User.gif" EXPANDEDIMAGEURL="images/folderopen.gif" id="N_680" Qlevel="0" Ilevel="0" Ulevel="0" Dlevel="0" Clevel="0" />
  </treenode1>
  <treenode1 text="意見反應管理(漏氣搶修)" IMAGEURL="images/User.gif" EXPANDEDIMAGEURL="images/folderopen.gif" id="N_684" Qlevel="0" Ilevel="0" Ulevel="0" Dlevel="0" Clevel="0">
    <treenode2 text="2.指派意見反映(漏氣搶修)" IMAGEURL="images/User.gif" EXPANDEDIMAGEURL="images/folderopen.gif" id="N_685" Qlevel="0" Ilevel="0" Ulevel="0" Dlevel="0" Clevel="0" />
    <treenode2 text="1.處理意見反映(漏氣搶修)" IMAGEURL="images/User.gif" EXPANDEDIMAGEURL="images/folderopen.gif" id="N_686" Qlevel="0" Ilevel="0" Ulevel="0" Dlevel="0" Clevel="0" />
    <treenode2 text="3.列印意見反映表(漏氣搶修)" IMAGEURL="images/User.gif" EXPANDEDIMAGEURL="images/folderopen.gif" id="N_687" Qlevel="0" Ilevel="0" Ulevel="0" Dlevel="0" Clevel="0" />
  </treenode1>
</TREENODES>