<?xml version="1.0" encoding="big5"?>
<LABOR LABOR_ID="1">
  <NAME>一級特派員</NAME>
  <IDNO>A123456789</IDNO>
  <BIRTH>1988/7/7</BIRTH>
  <SEX>1</SEX>
  <MARRI>1</MARRI>
  <ADDR_CITY>31</ADDR_CITY>
  <ADDR_ZIP>231</ADDR_ZIP>
  <ADDR>大同路１００號</ADDR>
  <TEL1>02-27273737</TEL1>
  <TEL2 />
  <E_MAIL>jerry@turbotech.com.tw</E_MAIL>
  <PASSWD>1234</PASSWD>
  <MOBILE />
  <USER_IDENFITY />
  <REVIEW_RGSTN>A10000</REVIEW_RGSTN>
  <REVIEW_ID>Ellen</REVIEW_ID>
  <REVIEW_DATE>2005/11/14</REVIEW_DATE>
  <REVIEW_STATE>3</REVIEW_STATE>
  <DEL_STATE>0</DEL_STATE>
  <FAX />
  <JOB_CENTER_ID>A10000</JOB_CENTER_ID>
  <CONTACT>000001</CONTACT>
  <FIRSTDATE>2005/11/14</FIRSTDATE>
  <E_MAIL_FLAG>1</E_MAIL_FLAG>
  <DATASOURCE>2</DATASOURCE>
  <NOTE />
  <IMPORT_DATE />
  <CONTACT_OTHER>000001</CONTACT_OTHER>
  <LAST_LOGIN>2005/11/29 上午 10:31:33</LAST_LOGIN>
  <APPROVE>1</APPROVE>
  <APPROVE_OTHER />
  <SEND_ORG1 />
  <SEND_ORG1_DATE />
  <GOV_LOGIN />
  <LABOR_ID>1</LABOR_ID>
  <FA_FALG>2</FA_FALG>
  <FA_DATE>2005/11/23</FA_DATE>
  <BIRTHDAY>1988/7/7</BIRTHDAY>
  <SEX>1</SEX>
  <EDGR>3</EDGR>
  <DEPTCD>8404</DEPTCD>
  <OCCUCD1>392201</OCCUCD1>
  <OCCUCD2>292206</OCCUCD2>
  <OCCUCD3>190990</OCCUCD3>
  <WKPLCD1>01</WKPLCD1>
  <WKPLCD2>31</WKPLCD2>
  <WKPLCD3>31</WKPLCD3>
  <SALARY_M>1</SALARY_M>
  <SALARY>30000</SALARY>
  <TRANDATE>2005/11/23 上午 11:27:25</TRANDATE>
  <CLOSE_REASON>A</CLOSE_REASON>
  <CLOSE_ROLE>2</CLOSE_ROLE>
  <CLOSE_USER_ID>A10000001</CLOSE_USER_ID>
  <WKPLZIP1>001</WKPLZIP1>
  <WKPLZIP2>235</WKPLZIP2>
  <WKPLZIP3>231</WKPLZIP3>
  <CLOSE_RGSTN>A10000</CLOSE_RGSTN>
  <DEPT_OTHER />
  <DEPTCD2 />
  <DEPT_OTHER2 />
  <DEPTCD3 />
  <DEPT_OTHER3 />
  <EDGR_OTHER />
  <OCCU_DESC1 />
  <OCCU_DESC2 />
  <OCCU_DESC3 />
  <CJOB_NO1>1304</CJOB_NO1>
  <CJOB_NO2>1302</CJOB_NO2>
  <CJOB_NO3>1201</CJOB_NO3>
  <BUSI_ID1 />
  <BUSI_ID2 />
  <BUSI_ID3 />
  <CLOSE_REASON_OTHER />
  <LABOR_ID>1</LABOR_ID>
  <RGSTN>A10000</RGSTN>
  <USER_ID>Ellen</USER_ID>
  <RECNO>A10000200511000001</RECNO>
  <FIRSTDATE>2005/11/14 下午 10:28:13</FIRSTDATE>
  <RGDATE>2005/11/14 下午 10:28:13</RGDATE>
  <LOOK_TYPE />
  <NET>1</NET>
  <SOLDER>3</SOLDER>
  <GRADU>1</GRADU>
  <SCHOOL />
  <WORK_TIME>0000001</WORK_TIME>
  <PART_TIME>00000000</PART_TIME>
  <TRANNING />
  <ABILITY1>舌頭7尺長=.=</ABILITY1>
  <ABILITY2>手臂8尺長=.=</ABILITY2>
  <ABILITY3>頭髮9尺長=.=</ABILITY3>
  <EXPCD1 />
  <EXPYM1 />
  <EXPCD2 />
  <EXPYM2 />
  <DRI>23</DRI>
  <TECHCD1 />
  <TECHLV1 />
  <TECHCD2 />
  <TECHLV2 />
  <INDIVIDUAL />
  <FORLNG>20330</FORLNG>
  <FORLNG_OTH>泰雅語</FORLNG_OTH>
  <RESOU>2</RESOU>
  <DISABLED_CD />
  <DISABLED_LABEL>0</DISABLED_LABEL>
  <IF_COMMUTE_TIME>5</IF_COMMUTE_TIME>
  <JOIN_JOB>0</JOIN_JOB>
  <JOB_TYPE1 />
  <JOB_TYPE2 />
  <JOB_TYPE3 />
  <JOB_CLASS1 />
  <JOB_CLASS2 />
  <JOB_CLASS3 />
  <IF_USE_COMPUTER>1</IF_USE_COMPUTER>
  <USE_POWER>1110000</USE_POWER>
  <USE_OTHER />
  <IF_ECONOMY_STRESS>1</IF_ECONOMY_STRESS>
  <STRESS_TYPE>1001</STRESS_TYPE>
  <STRESS_OTHER>卡債</STRESS_OTHER>
  <JOB_LOCATION />
  <LEAVE_DATE />
  <LEAVE_LONG>0</LEAVE_LONG>
  <BEFORE_MONEY>0</BEFORE_MONEY>
  <USER_IDENTITY />
  <EXPWORK1 />
  <EXPWORK2 />
  <ONESELF>1</ONESELF>
  <TECH_OTHER />
  <SCHOOL_ID>1015</SCHOOL_ID>
  <SCHOOL_ID2 />
  <SCHOOL2 />
  <SCHOOL_ID3 />
  <SCHOOL3 />
  <GRADU2>1</GRADU2>
  <GRADU_YEAR2 />
  <GRADU3>1</GRADU3>
  <GRADU_YEAR3 />
  <GRADU_YEAR>200406</GRADU_YEAR>
  <IN_JOB>0</IN_JOB>
  <WISH_JOB_TYPE>1</WISH_JOB_TYPE>
  <WISH_JOB_DATE />
  <COLLEGE_GRADU_YEAR />
  <HIGH_GRADU_YEAR />
  <JOB_MONTHS>0</JOB_MONTHS>
  <CASE_SOURCE />
  <CASE_OTHER />
  <OTHER_DETAIL />
</LABOR>